Histopedia/__init__.py
Histopedia/history.py
Histopedia-0.0.5.dist-info/LICENSE
Histopedia-0.0.5.dist-info/METADATA
Histopedia-0.0.5.dist-info/WHEEL
Histopedia-0.0.5.dist-info/top_level.txt
Histopedia-0.0.5.dist-info/RECORD
