Metadata-Version: 2.1
Name: Histopedia
Version: 0.0.5
Summary: python package for scientific historical information
Home-page: https://github.com/PyndyalaCoder/Histopedia
Author: Siddhu Pendyala
Author-email: elcientifico.pendyala@hotmail.com
License: MIT
Project-URL: Bug Tracker, https://github.com/PyndyalaCoder/Histopedia/issues
License-File: LICENSE
Requires-Dist: requests
